zylch_cli/__init__.py
zylch_cli/api_client.py
zylch_cli/cli.py
zylch_cli/config.py
zylch_cli/local_storage.py
zylch_cli/modifier_queue.py
zylch_cli/oauth_handler.py
zylch_cli-0.9.2.dist-info/licenses/LICENSE
zylch_cli-0.9.2.dist-info/METADATA
zylch_cli-0.9.2.dist-info/WHEEL
zylch_cli-0.9.2.dist-info/entry_points.txt
zylch_cli-0.9.2.dist-info/top_level.txt
zylch_cli-0.9.2.dist-info/RECORD
