Metadata-Version: 2.4
Name: zylch-cli
Version: 0.9.2
Summary: Thin CLI client for Zylch AI - connects to Zylch API server
Author-email: Mario Alemi <mario@zylchai.com>
License: MIT
Project-URL: Homepage, https://zylchai.com
Project-URL: Repository, https://github.com/malemi/zylch-cli
Project-URL: Documentation, https://github.com/malemi/zylch-cli#readme
Keywords: cli,ai,email,calendar,assistant
Classifier: Development Status :: 4 - Beta
Classifier: Environment :: Console
Classifier: Intended Audience :: End Users/Desktop
Classifier: License :: OSI Approved :: MIT License
Classifier: Operating System :: OS Independent
Classifier: Programming Language :: Python :: 3
Classifier: Programming Language :: Python :: 3.11
Classifier: Programming Language :: Python :: 3.12
Classifier: Programming Language :: Python :: 3.13
Classifier: Topic :: Communications :: Email
Classifier: Topic :: Office/Business :: Scheduling
Requires-Python: >=3.11
License-File: LICENSE
Requires-Dist: requests>=2.31.0
Requires-Dist: pydantic>=2.5.0
Requires-Dist: pydantic-settings>=2.1.0
Requires-Dist: rich>=13.7.0
Requires-Dist: click>=8.1.7
Requires-Dist: prompt_toolkit>=3.0.0
Provides-Extra: dev
Requires-Dist: pytest>=7.4.3; extra == "dev"
Requires-Dist: pytest-asyncio>=0.21.1; extra == "dev"
Requires-Dist: black>=23.12.1; extra == "dev"
Requires-Dist: ruff>=0.1.8; extra == "dev"
Dynamic: license-file
